cursoFiap/__init__.py
cursoFiap/core.py
cursoFiap_package_robertoclj-1.0.1.dist-info/METADATA
cursoFiap_package_robertoclj-1.0.1.dist-info/WHEEL
cursoFiap_package_robertoclj-1.0.1.dist-info/top_level.txt
cursoFiap_package_robertoclj-1.0.1.dist-info/RECORD
