Metadata-Version: 2.1
Name: cursoFiap-package-robertoclj
Version: 1.0.1
Summary: Descricao da sua lib cursoFiap
Home-page: https://github.com/robertoclj/cursoFiap
Author: Roberto Costa Lima Jr
Author-email: robertoclj@gmail.com
License: MIT
Platform: UNKNOWN
